git_sha2/__init__.py
git_sha2/cli.py
git_sha2_tool-1.0.1.dist-info/METADATA
git_sha2_tool-1.0.1.dist-info/WHEEL
git_sha2_tool-1.0.1.dist-info/entry_points.txt
git_sha2_tool-1.0.1.dist-info/top_level.txt
git_sha2_tool-1.0.1.dist-info/RECORD
