Metadata-Version: 2.4
Name: git-sha2-tool
Version: 1.0.1
Summary: CLI to compute SHA-256 of files from Git URLs
Author: Vinayak Bipin Joshi
Author-email: Vinayak Bipin Joshi <vinayak.joshi6803@gmail.com>
License: MIT
Project-URL: Homepage, https://pypi.org/project/git-sha2-tool/
Project-URL: Repository, https://github.com/vinayakjoshi6803/git-sha2-tool
Requires-Python: >=3.7
Requires-Dist: requests
Dynamic: author
